nobuco/__init__.py
nobuco/commons.py
nobuco/convert.py
nobuco/funcs.py
nobuco/util.py
nobuco/addons/__init__.py
nobuco/addons/torch/__init__.py
nobuco/addons/torch/dense_image_warp.py
nobuco/addons/torch/depth_to_space.py
nobuco/addons/torch/space_to_depth.py
nobuco/addons/torch/util.py
nobuco/converters/__init__.py
nobuco/converters/channel_ordering.py
nobuco/converters/node_converter.py
nobuco/converters/scalars_to_tensors.py
nobuco/converters/tensor.py
nobuco/converters/type_cast.py
nobuco/converters/validation.py
nobuco/entity/__init__.py
nobuco/entity/keras.py
nobuco/entity/pytorch.py
nobuco/layers/__init__.py
nobuco/layers/channel_order.py
nobuco/layers/container.py
nobuco/layers/stub.py
nobuco/layers/weight.py
nobuco/locate/__init__.py
nobuco/locate/link.py
nobuco/locate/locate.py
nobuco/node_converters/__init__.py
nobuco/node_converters/activation.py
nobuco/node_converters/attention.py
nobuco/node_converters/boolean.py
nobuco/node_converters/boolean_mask.py
nobuco/node_converters/comparison.py
nobuco/node_converters/convolution.py
nobuco/node_converters/dropout.py
nobuco/node_converters/fft.py
nobuco/node_converters/grad.py
nobuco/node_converters/grid_sampling.py
nobuco/node_converters/interpolation.py
nobuco/node_converters/linear.py
nobuco/node_converters/math.py
nobuco/node_converters/misc.py
nobuco/node_converters/normalization.py
nobuco/node_converters/padding.py
nobuco/node_converters/pooling.py
nobuco/node_converters/recurrent.py
nobuco/node_converters/reduce.py
nobuco/node_converters/slice.py
nobuco/node_converters/tensor_broadcast.py
nobuco/node_converters/tensor_cast.py
nobuco/node_converters/tensor_creation.py
nobuco/node_converters/tensor_getattribute.py
nobuco/node_converters/tensor_manipulation.py
nobuco/node_converters/tensor_shape.py
nobuco/node_converters/torchvision.py
nobuco/trace/__init__.py
nobuco/trace/tensor_storage.py
nobuco/trace/trace.py
nobuco/vis/__init__.py
nobuco/vis/console_stylizer.py
nobuco/vis/html_stylizer.py
nobuco-0.17.0.dist-info/LICENSE
nobuco-0.17.0.dist-info/METADATA
nobuco-0.17.0.dist-info/WHEEL
nobuco-0.17.0.dist-info/top_level.txt
nobuco-0.17.0.dist-info/RECORD
