Metadata-Version: 2.2
Name: nobuco
Version: 0.17.0
Summary: Pytorch to Tensorflow conversion made intuitive
Author-email: Alexander Lutsenko <lex.lutsenko@gmail.com>
Project-URL: Homepage, https://github.com/AlexanderLutsenko/nobuco
Project-URL: Bug Tracker, https://github.com/AlexanderLutsenko/nobuco/issues
Keywords: pytorch,tensorflow,keras,converter
Classifier: Programming Language :: Python :: 3
Classifier: License :: OSI Approved :: MIT License
Classifier: Operating System :: OS Independent
Requires-Python: >=3.7
License-File: LICENSE
Requires-Dist: sty>=1.0.0
Requires-Dist: tqdm>=4.66.0
Requires-Dist: rich
Requires-Dist: numpy
